smrf_dev-0.11.7.dist-info/RECORD
smrf_dev-0.11.7.dist-info/METADATA
smrf_dev-0.11.7.dist-info/AUTHORS.md
smrf_dev-0.11.7.dist-info/top_level.txt
smrf_dev-0.11.7.dist-info/WHEEL
smrf_dev-0.11.7.dist-info/LICENSE
smrf_dev.libs/libgomp-a34b3233.so.1.0.0
smrf_dev-0.11.7.data/scripts/gen_maxus
smrf_dev-0.11.7.data/scripts/run_smrf
smrf_dev-0.11.7.data/scripts/update_configs
smrf/__init__.py
smrf/data/gridded_input.py
smrf/data/__init__.py
smrf/data/netcdf.py
smrf/data/csv.py
smrf/data/input_data.py
smrf/data/hrrr_grib.py
smrf/data/load_topo.py
smrf/data/wrf.py
smrf/utils/__init__.py
smrf/utils/utils.py
smrf/utils/queue.py
smrf/utils/io.py
smrf/utils/pycompat.py
smrf/utils/wind/model.py
smrf/utils/wind/wind_header.h
smrf/utils/wind/wind_c.cpython-37m-x86_64-linux-gnu.so
smrf/utils/wind/__init__.py
smrf/utils/wind/breshen.h
smrf/utils/wind/wind_c.c
smrf/utils/wind/breshen.c
smrf/utils/wind/calc_wind.c
smrf/utils/wind/wind_c.pyx
smrf/output/__init__.py
smrf/output/output_hru.py
smrf/output/output_netcdf.py
smrf/distribute/__init__.py
smrf/distribute/vapor_pressure.py
smrf/distribute/cloud_factor.py
smrf/distribute/albedo.py
smrf/distribute/precipitation.py
smrf/distribute/image_data.py
smrf/distribute/thermal.py
smrf/distribute/soil_temp.py
smrf/distribute/air_temp.py
smrf/distribute/solar.py
smrf/distribute/wind/wind_ninja.py
smrf/distribute/wind/__init__.py
smrf/distribute/wind/winstral.py
smrf/distribute/wind/wind.py
smrf/framework/__init__.py
smrf/framework/model_framework.py
smrf/framework/CoreConfig.ini
smrf/framework/recipes.ini
smrf/framework/changelog.ini
smrf/framework/.qotw
smrf/framework/logger.py
smrf/framework/art.py
smrf/envphys/sunang.py
smrf/envphys/snow.py
smrf/envphys/__init__.py
smrf/envphys/vapor_pressure.py
smrf/envphys/constants.py
smrf/envphys/albedo.py
smrf/envphys/storms.py
smrf/envphys/precip.py
smrf/envphys/nasde_model/susong_1999.py
smrf/envphys/nasde_model/marks_2017.py
smrf/envphys/nasde_model/__init__.py
smrf/envphys/nasde_model/piecewise_suosong_1999.py
smrf/envphys/nasde_model/utils.py
smrf/envphys/solar/model.py
smrf/envphys/solar/__init__.py
smrf/envphys/solar/cloud.py
