Metadata-Version: 2.1
Name: smrf-dev
Version: 0.11.7
Summary: Distributed snow modeling for water resources
Home-page: https://github.com/USDA-ARS-NWRC/smrf
Author: USDA ARS NWRC
Author-email: snow@ars.usda.gov
License: CC0 1.0
Keywords: smrf
Platform: UNKNOWN
Classifier: Development Status :: 2 - Pre-Alpha
Classifier: Intended Audience :: Developers
Classifier: Natural Language :: English
Classifier: License :: CC0 1.0 Universal (CC0 1.0) Public Domain Dedication
Classifier: Programming Language :: Python :: 3
Classifier: Programming Language :: Python :: 3.6
Classifier: Programming Language :: Python :: 3.7
Classifier: Programming Language :: Python :: 3.8
Classifier: Programming Language :: Python :: 3.9
Requires-Python: >=3.6
Provides-Extra: docs
Provides-Extra: tests
